cellseg_gsontools/__init__.py
cellseg_gsontools/apply.py
cellseg_gsontools/character.py
cellseg_gsontools/clustering.py
cellseg_gsontools/data/__init__.py
cellseg_gsontools/data/cervix_cells.feather
cellseg_gsontools/data/cervix_tissue.feather
cellseg_gsontools/data/fetch.py
cellseg_gsontools/data/gland_areas.feather
cellseg_gsontools/data/gland_cells.feather
cellseg_gsontools/data/merge_data/area/x-41000_y-82000_areas.feather
cellseg_gsontools/data/merge_data/area/x-41000_y-83000_areas.feather
cellseg_gsontools/data/merge_data/area/x-41000_y-84000_areas.feather
cellseg_gsontools/data/merge_data/area/x-42000_y-82000_areas.feather
cellseg_gsontools/data/merge_data/area/x-42000_y-83000_areas.feather
cellseg_gsontools/data/merge_data/area/x-42000_y-84000_areas.feather
cellseg_gsontools/data/merge_data/area/x-43000_y-82000_areas.feather
cellseg_gsontools/data/merge_data/area/x-43000_y-83000_areas.feather
cellseg_gsontools/data/merge_data/area/x-43000_y-84000_areas.feather
cellseg_gsontools/data/merge_data/cell/x-41000_y-87000_cells.feather
cellseg_gsontools/data/merge_data/cell/x-41000_y-88000_cells.feather
cellseg_gsontools/data/merge_data/cell/x-41000_y-89000_cells.feather
cellseg_gsontools/data/merge_data/cell/x-42000_y-86000_cells.feather
cellseg_gsontools/data/merge_data/cell/x-42000_y-87000_cells.feather
cellseg_gsontools/data/merge_data/cell/x-42000_y-88000_cells.feather
cellseg_gsontools/data/merge_data/cell/x-43000_y-86000_cells.feather
cellseg_gsontools/data/merge_data/cell/x-43000_y-87000_cells.feather
cellseg_gsontools/data/merge_data/cell/x-43000_y-88000_cells.feather
cellseg_gsontools/data/ts_iface_areas.feather
cellseg_gsontools/data/ts_iface_cells.feather
cellseg_gsontools/diversity.py
cellseg_gsontools/geometry/__init__.py
cellseg_gsontools/geometry/axis.py
cellseg_gsontools/geometry/circle.py
cellseg_gsontools/geometry/mean_shape.py
cellseg_gsontools/geometry/shape_metrics.py
cellseg_gsontools/graphs.py
cellseg_gsontools/grid.py
cellseg_gsontools-0.1.8.dist-info/LICENSE
cellseg_gsontools-0.1.8.dist-info/METADATA
cellseg_gsontools-0.1.8.dist-info/WHEEL
cellseg_gsontools-0.1.8.dist-info/RECORD
