Metadata-Version: 2.1
Name: cellseg-gsontools
Version: 0.1.8
Summary: Toolbelt for merging and extracting features from geojson masks.
Home-page: https://github.com/okunator/cellseg_gsontools
Author: Okunator
Author-email: oskari.lehtonen@helsinki.fi
Requires-Python: >=3.10,<4.0
Classifier: Programming Language :: Python :: 3
Classifier: Programming Language :: Python :: 3.10
Classifier: Programming Language :: Python :: 3.11
Classifier: Programming Language :: Python :: 3.12
Requires-Dist: geojson (>=2.5.0,<3.0.0)
Requires-Dist: geopandas (>=1.0.1,<2.0.0)
Requires-Dist: h3 (>=3.7.6,<4.0.0)
Requires-Dist: libpysal (==4.9.2)
Requires-Dist: mapclassify (>=2.5.0,<3.0.0)
Requires-Dist: matplotlib (>=3.6.1,<4.0.0)
Requires-Dist: numba (>=0.57.1,<0.58.0)
Requires-Dist: numpy (>=1.23.4,<2.0.0)
Requires-Dist: opencv-python (>=4.2.0.32,<5.0.0.0)
Requires-Dist: pandarallel (>=1.6.4,<2.0.0)
Requires-Dist: pathos (>=0.3.1,<0.4.0)
Requires-Dist: pyarrow (>=14.0.0,<15.0.0)
Requires-Dist: scikit-image (>=0.19.3,<0.20.0)
Requires-Dist: scikit-learn (>=1.3.0)
Requires-Dist: scipy (>=1.9.2,<2.0.0)
Requires-Dist: shapely (>=2.0)
Requires-Dist: tqdm (>=4.64.1,<5.0.0)
Project-URL: Repository, https://github.com/okunator/cellseg_gsontools
